tap_dz_dynamodb/__init__.py
tap_dz_dynamodb/deserialize.py
tap_dz_dynamodb/discover.py
tap_dz_dynamodb/dynamodb.py
tap_dz_dynamodb/sync.py
tap_dz_dynamodb/sync_strategies/__init__.py
tap_dz_dynamodb/sync_strategies/full_table.py
tap_dz_dynamodb/sync_strategies/log_based.py
tap_dz_dynamodb-1.3.6.dist-info/LICENSE
tap_dz_dynamodb-1.3.6.dist-info/METADATA
tap_dz_dynamodb-1.3.6.dist-info/WHEEL
tap_dz_dynamodb-1.3.6.dist-info/entry_points.txt
tap_dz_dynamodb-1.3.6.dist-info/top_level.txt
tap_dz_dynamodb-1.3.6.dist-info/RECORD
